aimanager_hjy/__init__.py
aimanager_hjy/core/__init__.py
aimanager_hjy/core/config.py
aimanager_hjy/core/database.py
aimanager_hjy/core/file_upload.py
aimanager_hjy/core/manager.py
aimanager_hjy/core/route.py
aimanager_hjy/core/validation.py
aimanager_hjy-0.3.0.dist-info/licenses/LICENSE
aimanager_hjy-0.3.0.dist-info/METADATA
aimanager_hjy-0.3.0.dist-info/WHEEL
aimanager_hjy-0.3.0.dist-info/top_level.txt
aimanager_hjy-0.3.0.dist-info/RECORD
