Metadata-Version: 2.4
Name: aimanager_hjy
Version: 0.3.0
Summary: AI服务管理包 - 统一的AI模型调用接口
Home-page: https://github.com/hjy/aimanager_hjy
Author: hjy
Author-email: hjy@example.com
Classifier: Development Status :: 3 - Alpha
Classifier: Intended Audience :: Developers
Classifier: License :: OSI Approved :: MIT License
Classifier: Operating System :: OS Independent
Classifier: Programming Language :: Python :: 3
Classifier: Programming Language :: Python :: 3.8
Classifier: Programming Language :: Python :: 3.9
Classifier: Programming Language :: Python :: 3.10
Classifier: Programming Language :: Python :: 3.11
Classifier: Programming Language :: Python :: 3.12
Classifier: Programming Language :: Python :: 3.13
Requires-Python: >=3.8
License-File: LICENSE
Requires-Dist: pydantic<3,>=2.0
Requires-Dist: pydantic-settings<3,>=2.2
Requires-Dist: httpx<1,>=0.27
Requires-Dist: loguru<1,>=0.7
Requires-Dist: mysql-connector-python<9,>=8.3
Requires-Dist: cryptography<43,>=41
Requires-Dist: oss2<3,>=2.18
Provides-Extra: dev
Requires-Dist: pytest>=7.0; extra == "dev"
Requires-Dist: pytest-asyncio>=0.21; extra == "dev"
Requires-Dist: black>=22.0; extra == "dev"
Requires-Dist: isort>=5.0; extra == "dev"
Requires-Dist: flake8>=4.0; extra == "dev"
Dynamic: author
Dynamic: author-email
Dynamic: classifier
Dynamic: description
Dynamic: description-content-type
Dynamic: home-page
Dynamic: license-file
Dynamic: provides-extra
Dynamic: requires-dist
Dynamic: requires-python
Dynamic: summary
